mahdiyeh_mbca
